CHANGES
MANIFEST.in
README
ez_setup.py
setup.cfg
setup.py
doc/libGWAS-API.pdf
libgwas/__init__.py
libgwas/bed_parser.py
libgwas/boundary.py
libgwas/data_parser.py
libgwas/exceptions.py
libgwas/impute_parser.py
libgwas/locus.py
libgwas/mach_parser.py
libgwas/parsed_locus.py
libgwas/pedigree_parser.py
libgwas/pheno_covar.py
libgwas/snp_boundary_check.py
libgwas/standardizer.py
libgwas/transposed_pedigree_parser.py
libgwas.egg-info/PKG-INFO
libgwas.egg-info/SOURCES.txt
libgwas.egg-info/dependency_links.txt
libgwas.egg-info/requires.txt
libgwas.egg-info/top_level.txt
tests/__init__.py
tests/bed_parser_test.py
tests/test_boundary.py
tests/test_impute_parser.py
tests/test_locus.py
tests/test_mach_parser.py
tests/test_pedigree_parser.py
tests/test_phenocovar.py
tests/test_transped_parser.py