Metadata-Version: 1.1
Name: libgwas
Version: 1.0.0
Summary: ['GWAS Parser Library']
Home-page: https://github.com/edwards-lab/libGWAS
Author: Eric Torstenson
Author-email: eric.s.torstenson@vanderbilt.edu
License: GPL
Download-URL: https://github.com/edwards-lab/libGWAS/archive/v1.0.0.tar.gz
Keywords: GWAS,genetic analysis
Platform: UNKNOWN
Classifier: Development Status :: 4 - Beta
Classifier: Topic :: Utilities
Classifier: License :: OSI Approved :: GNU General Public License v3 or later (GPLv3+)
Classifier: Topic :: Scientific/Engineering :: Bio-Informatics
Classifier: Topic :: Software Development :: Libraries
Classifier: Programming Language :: Python :: 2.7
